django_grunted_assets-0.2.1.dist-info/DESCRIPTION.rst
django_grunted_assets-0.2.1.dist-info/METADATA
django_grunted_assets-0.2.1.dist-info/metadata.json
django_grunted_assets-0.2.1.dist-info/RECORD
django_grunted_assets-0.2.1.dist-info/top_level.txt
django_grunted_assets-0.2.1.dist-info/WHEEL
grunted_assets/__init__.py
grunted_assets/templatetags/__init__.py
grunted_assets/templatetags/grunted_assets.py
