Metadata-Version: 2.0
Name: django-grunted-assets
Version: 0.2.1
Summary: A Django app for simplifing the use of grunt for your asset flow
Home-page: https://github.com/tino/django-grunted-assets
Author: Tino de Bruijn
Author-email: tinodb@gmail.com
License: See LICENSE.txt
Platform: UNKNOWN
Classifier: Intended Audience :: Developers
Classifier: License :: OSI Approved :: MIT License
Classifier: Programming Language :: Python
Classifier: Programming Language :: Python :: 2.6
Classifier: Programming Language :: Python :: 2.7
Classifier: Framework :: Django
Classifier: Development Status :: 4 - Beta
Classifier: Operating System :: OS Independent
